scale/olm/__init__.py
scale/olm/__main__.py
scale/olm/assemble.py
scale/olm/check.py
scale/olm/contrib.py
scale/olm/core.py
scale/olm/internal.py
scale/olm/report.py
scale/olm/run.py
scale/olm/generate/__init__.py
scale/olm/generate/comp.py
scale/olm/generate/dynamic.py
scale/olm/generate/root.py
scale/olm/generate/states.py
scale/olm/generate/static.py
scale/olm/generate/time.py
scale/olm/templates/model/origami/system-mox.jt.inp
scale/olm/templates/model/origami/system-uox.jt.inp
scale/olm/templates/model/triton/pin-mox.jt.inp
scale/olm/templates/model/triton/pin-uox.jt.inp
scale/olm/templates/report/scale-short.jt.rst
scale/olm/variants/mox_quick/config.olm.json
scale/olm/variants/mox_quick/files.json
scale/olm/variants/uox_quick/config.olm.json
scale/olm/variants/uox_quick/files.json
scale_olm-0.14.2.dist-info/licenses/LICENSE
scale_olm-0.14.2.dist-info/METADATA
scale_olm-0.14.2.dist-info/WHEEL
scale_olm-0.14.2.dist-info/entry_points.txt
scale_olm-0.14.2.dist-info/top_level.txt
scale_olm-0.14.2.dist-info/RECORD
