Metadata-Version: 2.4
Name: scale-olm
Version: 0.14.2
Summary: ORIGEN Library Manager: A tool for building and managing ORIGEN reactor data libraries
Author-email: William Wieselquist <ww5@ornl.gov>
License: Copyright 2024 UT-Battelle, LLC
Project-URL: documentation, https://scale-olm.readthedocs.io
Project-URL: bug-tracker, https://github.com/wawiesel/olm/issues
Project-URL: source, https://github.com/wawiesel/olm
Keywords: SCALE,ORIGEN,Library
Classifier: Development Status :: 1 - Planning
Classifier: Intended Audience :: Science/Research
Classifier: Topic :: Scientific/Engineering :: Physics
Classifier: Programming Language :: Python :: 3 :: Only
Classifier: License :: OSI Approved :: BSD License
Classifier: Operating System :: OS Independent
Requires-Python: >=3.9
License-File: LICENSE
Requires-Dist: click
Requires-Dist: matplotlib
Requires-Dist: scipy
Requires-Dist: numpy
Requires-Dist: pytest
Requires-Dist: pydantic
Dynamic: license-file
